[
    {
       "Climate":"H",
       "Country":"Texas",
       "Price":"S",
       "Time of Year":"S",
       "url":"images/austin.jpg",
       "Landscape":"C",
       "City":"Austin"
    },
    {
       "Climate":"H",
       "Country":"Virginia",
       "Price":"S",
       "Time of Year":"S",
       "Image URL":"images/norfolk.jpg",
       "Landscape":"N",
       "City":"Norfolk"
    },
    {
       "Climate":"H",
       "Country":"Italy",
       "Price":"I",
       "Time of Year":"S",
       "Image URL":"https://unsplash.com/search/photos/turin?photo=SjhF0GMI0zY",
       "Landscape":"C",
       "City":"Turin"
    },
    {
       "Climate":"H",
       "Country":"Bermuda",
       "Price":"I",
       "Time of Year":"S",
       "Image URL":"https://unsplash.com/search/photos/beach?photo=QNmdDWCWKBw",
       "Landscape":"N",
       "City":"Bermuda"
    },
    {
       "Climate":"C",
       "Country":"Northern Ireland",
       "Price":"S",
       "Time of Year":"S",
       "Image URL":"https://unsplash.com/search/photos/pint?photo=XliG1JGo7oo",
       "Landscape":"C",
       "City":"Belfast"
    },
    {
       "Climate":"C",
       "Country":"Canada",
       "Price":"S",
       "Time of Year":"S",
       "Image URL":"https://unsplash.com/search/photos/newfoundland?photo=Fq3WTAAEFHg",
       "Landscape":"N",
       "City":"St.John's"
    },
    {
       "Climate":"C",
       "Country":"Uruguay",
       "Price":"I",
       "Time of Year":"S",
       "Image URL":"https://unsplash.com/search/photos/uruguay?photo=g-9IQxBZ0vs",
       "Landscape":"C",
       "City":"Montevideo"
    },
    {
       "Climate":"C",
       "Country":"New Zealand",
       "Price":"I",
       "Time of Year":"S",
       "Image URL":"https://unsplash.com/search/photos/new-zealand?photo=5krgkKmeiMI",
       "Landscape":"N",
       "City":"Queenstown"
    },
    {
       "Climate":"H",
       "Country":"Ecuador",
       "Price":"S",
       "Time of Year":"W",
       "Image URL":"https://unsplash.com/search/photos/ecuador?photo=qOmxP7W8svM",
       "Landscape":"C",
       "City":"Guayaquil"
    },
    {
       "Climate":"H",
       "Country":"Brazil",
       "Price":"S",
       "Time of Year":"W",
       "Image URL":"https://unsplash.com/search/photos/tropical?photo=U6t80TWJ1DM",
       "Landscape":"N",
       "City":"Angra dos Reis"
    },
    {
       "Climate":"H",
       "Country":"South Africa",
       "Price":"I",
       "Time of Year":"W",
       "Image URL":"https://unsplash.com/search/photos/cape-town?photo=6V19Uy-tUhs",
       "Landscape":"C",
       "City":"Cape Town"
    },
    {
       "Climate":"H",
       "Country":"Australia",
       "Price":"I",
       "Time of Year":"W",
       "Image URL":"https://unsplash.com/search/photos/australia?photo=Ybd8rsQTMKA",
       "Landscape":"N",
       "City":"Perth"
    },
    {
       "Climate":"C",
       "Country":"Canada",
       "Price":"S",
       "Time of Year":"W",
       "Image URL":"https://unsplash.com/search/photos/quebec?photo=6-828bYztjw",
       "Landscape":"C",
       "City":"Quebec City"
    },
    {
       "Climate":"C",
       "Country":"USA",
       "Price":"S",
       "Time of Year":"W",
       "Image URL":"https://unsplash.com/search/photos/skiing?photo=qVKLnAbqZ_0",
       "Landscape":"N",
       "City":"Jackson Hole"
    },
    {
       "Climate":"C",
       "Country":"Germany",
       "Price":"I",
       "Time of Year":"W",
       "Image URL":"https://unsplash.com/search/photos/hamburg?photo=NE979IvnG-I",
       "Landscape":"C",
       "City":"Hamburg"
    },
    {
       "Climate":"C",
       "Country":"Iceland",
       "Price":"I",
       "Time of Year":"W",
       "Image URL":"https://unsplash.com/search/photos/hottub?photo=mFj2q7BSgLc",
       "Landscape":"N",
       "City":"Reykjavic"
    },
    {
       "Climate":"H",
       "Country":"USA",
       "Price":"S",
       "Time of Year":"S",
       "Image URL":"images/austin.jpg",
       "Landscape":"C",
       "City":"Fort Lauderdale"
    },
    {
       "Climate":"H",
       "Country":"USA",
       "Price":"S",
       "Time of Year":"S",
       "Image URL":"https://unsplash.com/search/photos/arizona?photo=7-xbbchQPaQ",
       "Landscape":"N",
       "City":"Tucson"
    },
    {
       "Climate":"H",
       "Country":"Spain",
       "Price":"I",
       "Time of Year":"S",
       "Image URL":"https://unsplash.com/search/photos/madrid?photo=QYeEoTv6Gbw",
       "Landscape":"C",
       "City":"Madrid"
    },
    {
       "Climate":"H",
       "Country":"BVI",
       "Price":"I",
       "Time of Year":"S",
       "Image URL":"https://unsplash.com/search/photos/tortola?photo=toB2qdSCi5g",
       "Landscape":"N",
       "City":"Tortola"
    },
    {
       "Climate":"C",
       "Country":"Canada",
       "Price":"S",
       "Time of Year":"S",
       "Image URL":"https://unsplash.com/search/photos/tulips?photo=Nh9WIEBbvmk",
       "Landscape":"C",
       "City":"Ottawa"
    },
    {
       "Climate":"C",
       "Country":"Canada",
       "Price":"S",
       "Time of Year":"S",
       "Image URL":"https://unsplash.com/search/photos/fjord?photo=oOFrXiz8-0A",
       "Landscape":"N",
       "City":"Tadoussac"
    },
    {
       "Climate":"C",
       "Country":"Argentina",
       "Price":"I",
       "Time of Year":"S",
       "Image URL":"https://unsplash.com/collections/881499/buenos-aires?photo=mmuMa7VXL1Y",
       "Landscape":"C",
       "City":"Buenos Aires"
    },
    {
       "Climate":"C",
       "Country":"Argentina",
       "Price":"I",
       "Time of Year":"S",
       "Image URL":"https://unsplash.com/search/photos/argentina?photo=L9RtyL_hzUg",
       "Landscape":"N",
       "City":"Florianapolis"
    },
    {
       "Climate":"H",
       "Country":"Morocco",
       "Price":"S",
       "Time of Year":"W",
       "Image URL":"https://unsplash.com/search/photos/marrakesh?photo=bnXUaEq9xYQ",
       "Landscape":"C",
       "City":"Marrakesh"
    },
    {
       "Climate":"H",
       "Country":"Dominican Republic",
       "Price":"S",
       "Time of Year":"W",
       "Image URL":"https://unsplash.com/photos/twlcYzNOUco",
       "Landscape":"N",
       "City":"Punta Cana"
    },
    {
       "Climate":"H",
       "Country":"Brazil",
       "Price":"I",
       "Time of Year":"W",
       "Image URL":"https://unsplash.com/photos/9Vypg4Imz-Q",
       "Landscape":"C",
       "City":"Rio di Janeiro"
    },
    {
       "Climate":"H",
       "Country":"Seychelles",
       "Price":"I",
       "Time of Year":"W",
       "Image URL":"https://unsplash.com/photos/muvtuYRwRRU",
       "Landscape":"N",
       "City":"Victoria"
    },
    {
       "Climate":"C",
       "Country":"USA",
       "Price":"S",
       "Time of Year":"W",
       "Image URL":"https://unsplash.com/search/photos/chicago?photo=Ye60h3tJuU0",
       "Landscape":"C",
       "City":"Chicago"
    },
    {
       "Climate":"C",
       "Country":"Canada",
       "Price":"S",
       "Time of Year":"W",
       "Image URL":"https://unsplash.com/search/photos/ski?photo=R3tHkgwYaic",
       "Landscape":"N",
       "City":"Collingwood"
    },
    {
       "Climate":"C",
       "Country":"Holland",
       "Price":"I",
       "Time of Year":"W",
       "Image URL":"https://unsplash.com/search/photos/amsterdam?photo=eP93fjCLv4g",
       "Landscape":"C",
       "City":"Amsterdam"
    },
    {
       "Climate":"C",
       "Country":"Norway",
       "Price":"I",
       "Time of Year":"W",
       "Image URL":"https://unsplash.com/search/photos/norway?photo=QSQ43lRbV6E",
       "Landscape":"N",
       "City":"Bergen"
    }
 ]
